README.md
setup.py
check_spyder/__init__.py
check_spyder/check_spyder.py
check_spyder.egg-info/PKG-INFO
check_spyder.egg-info/SOURCES.txt
check_spyder.egg-info/dependency_links.txt
check_spyder.egg-info/top_level.txt