Metadata-Version: 2.1
Name: check-spyder
Version: 0.15
Summary: Library to detect if you are using Spyder IDE or not.
Home-page: https://github.com/javierzurdo/Check_Spyder
Author: Javier S. Zurdo
Classifier: Programming Language :: Python :: 3
Classifier: License :: OSI Approved :: MIT License
Classifier: Operating System :: OS Independent
Requires-Python: >=3.6
